radiverse/__init__.py
radiverse/windowing.py
radiverse-0.1.0.dist-info/LICENSE
radiverse-0.1.0.dist-info/METADATA
radiverse-0.1.0.dist-info/WHEEL
radiverse-0.1.0.dist-info/top_level.txt
radiverse-0.1.0.dist-info/RECORD
