Metadata-Version: 2.1
Name: radiverse
Version: 0.1.0
Summary: A Python package for DICOM image processing.
Author-email: shujuecn <yinlin2824@gmail.com>
License: GNU GENERAL PUBLIC LICENSE
Project-URL: Homepage, https://github.com/shujuecn/radiverse
Keywords: dicom,medical imaging,image processing
Classifier: Programming Language :: Python :: 3
Classifier: License :: OSI Approved :: MIT License
Classifier: Operating System :: OS Independent
Requires-Python: >=3.6
License-File: LICENSE
Requires-Dist: numpy
Requires-Dist: pydicom
Requires-Dist: pillow
Requires-Dist: matplotlib
